{
  "version": "6.1.0",
  "flags": {},
  "shapes": [
    {
      "label": "face",
      "points": [
        [
          815.4054054054054,
          392.7027027027027
        ],
        [
          1004.5945945945946,
          641.3513513513512
        ]
      ],
      "group_id": null,
      "description": "",
      "shape_type": "rectangle",
      "flags": {},
      "mask": null
    }
  ],
  "imagePath": "..\\images\\0635f4f1-39b9-11f1-a32f-48e7daa73ab0.jpg",
  "imageData": null,
  "imageHeight": 1080,
  "imageWidth": 1920
}